promptsmiles/__init__.py
promptsmiles/samplers.py
promptsmiles/utils.py
promptsmiles-1.7.2.dist-info/licenses/LICENSE
promptsmiles-1.7.2.dist-info/METADATA
promptsmiles-1.7.2.dist-info/WHEEL
promptsmiles-1.7.2.dist-info/top_level.txt
promptsmiles-1.7.2.dist-info/RECORD
