Metadata-Version: 2.4
Name: promptsmiles
Version: 1.7.2
Summary: A conveniant package to manipulate SMILES strings for iterative prompting with chemical language models.
Author-email: Morgan Thomas <morganthomas263@gmail.com>
License-Expression: Apache-2.0
Project-URL: Homepage, https://github.com/compsciencelab/PromptSMILES
Project-URL: Issues, https://github.com/compsciencelab/PromptSMILES/issues
Keywords: SMILES,Chemical language models,De novo,Constrained de novo,chemistry,drug design
Classifier: Development Status :: 4 - Beta
Classifier: Programming Language :: Python :: 3
Classifier: Programming Language :: Python :: 3.7
Classifier: Programming Language :: Python :: 3.8
Classifier: Programming Language :: Python :: 3.9
Classifier: Programming Language :: Python :: 3.10
Classifier: Programming Language :: Python :: 3.11
Classifier: Programming Language :: Python :: 3.12
Classifier: Operating System :: OS Independent
Requires-Python: >=3.7
License-File: LICENSE
Requires-Dist: rdkit>=2022
Dynamic: license-file
